<BackupInst xmlns="http://www.microsoft.com/GroupPolicy/GPOOperations/Manifest"><GPOGuid><![CDATA[{C3E7A722-8430-4B63-A81F-4A44D20EC3C2}]]></GPOGuid><GPODomain><![CDATA[itisfine.lab]]></GPODomain><GPODomainGuid><![CDATA[{e361f50d-f328-4f85-abe6-8dd69ff693a4}]]></GPODomainGuid><GPODomainController><![CDATA[dc1.itisfine.lab]]></GPODomainController><BackupTime><![CDATA[2020-12-11T11:48:52]]></BackupTime><ID><![CDATA[{DF49753E-5B3F-49A1-A651-FFD902727198}]]></ID><Comment><![CDATA[WEF Server]]></Comment><GPODisplayName><![CDATA[Windows Event Forwarding Server]]></GPODisplayName></BackupInst>
